django_orm_plus/__init__.py
django_orm_plus/_bulk.py
django_orm_plus/_config.py
django_orm_plus/_fetch_related.py
django_orm_plus/_strict_mode.py
django_orm_plus/_util.py
django_orm_plus/apps.py
django_orm_plus/exceptions.py
django_orm_plus/mixins.py
django_orm_plus-0.1.0b4.dist-info/LICENSE
django_orm_plus-0.1.0b4.dist-info/METADATA
django_orm_plus-0.1.0b4.dist-info/WHEEL
django_orm_plus-0.1.0b4.dist-info/top_level.txt
django_orm_plus-0.1.0b4.dist-info/RECORD
